{
  "__version__": "1.0.0",
  "information": {
    "customSplash": {
      "id": "customSplash",
      "label": "customSplash",
      "enable": true,
      "customSplash": {
        "complete": false,
        "form": "https://creator-api.cocos.com/api/form/show?sid=cea79fa9ad7e78825dfd5a205ef4b2d9"
      }
    },
    "removeSplash": {
      "id": "removeSplash",
      "label": "removeSplash",
      "enable": true,
      "removeSplash": {
        "complete": false,
        "form": "https://creator-api.cocos.com/api/form/show?sid=cea79fa9ad7e78825dfd5a205ef4b2d9"
      }
    }
  }
}
